libervia/VERSION
libervia/__init__.py
libervia/common/__init__.py
libervia/common/constants.py
libervia/pages/_bridge/page_meta.py
libervia/pages/_browser/aio_bridge.py
libervia/pages/_browser/alt_media_player.py
libervia/pages/_browser/bridge.py
libervia/pages/_browser/cache.py
libervia/pages/_browser/dialog.py
libervia/pages/_browser/editor.py
libervia/pages/_browser/invitation.py
libervia/pages/_browser/loading.py
libervia/pages/_browser/slideshow.py
libervia/pages/_browser/template.py
libervia/pages/_browser/tmp_aio.py
libervia/pages/app/page_meta.py
libervia/pages/blog/page_meta.py
libervia/pages/blog/edit/page_meta.py
libervia/pages/blog/edit/_browser/__init__.py
libervia/pages/blog/view/page_meta.py
libervia/pages/blog/view/_browser/__init__.py
libervia/pages/blog/view/atom.xml/page_meta.py
libervia/pages/chat/page_meta.py
libervia/pages/chat/select/page_meta.py
libervia/pages/embed/page_meta.py
libervia/pages/events/page_meta.py
libervia/pages/events/_browser/__init__.py
libervia/pages/events/admin/page_meta.py
libervia/pages/events/new/page_meta.py
libervia/pages/events/rsvp/page_meta.py
libervia/pages/events/view/page_meta.py
libervia/pages/files/page_meta.py
libervia/pages/files/list/page_meta.py
libervia/pages/files/view/page_meta.py
libervia/pages/forums/page_meta.py
libervia/pages/forums/list/page_meta.py
libervia/pages/forums/topics/page_meta.py
libervia/pages/forums/topics/new/page_meta.py
libervia/pages/forums/topics/new/_browser/__init__.py
libervia/pages/forums/view/page_meta.py
libervia/pages/g/page_meta.py
libervia/pages/g/e/page_meta.py
libervia/pages/lists/page_meta.py
libervia/pages/lists/_browser/__init__.py
libervia/pages/lists/create/page_meta.py
libervia/pages/lists/create_from_tpl/page_meta.py
libervia/pages/lists/edit/page_meta.py
libervia/pages/lists/new/page_meta.py
libervia/pages/lists/view/page_meta.py
libervia/pages/lists/view/_browser/__init__.py
libervia/pages/lists/view_item/page_meta.py
libervia_web-0.8.0.dist-info/COPYING
libervia_web-0.8.0.dist-info/METADATA
libervia_web-0.8.0.dist-info/WHEEL
libervia_web-0.8.0.dist-info/entry_points.txt
libervia_web-0.8.0.dist-info/top_level.txt
libervia_web-0.8.0.dist-info/RECORD
