Metadata-Version: 2.1
Name: libervia-web
Version: 0.8.0
Summary: Web frontend for Libervia
Home-page: https://www.salut-a-toi.org
Author: Association « Salut à Toi »
Author-email: contact@goffi.org
License: UNKNOWN
Platform: UNKNOWN
Classifier: Programming Language :: Python :: 3 :: Only
Classifier: Programming Language :: Python :: 3.7
Classifier: Programming Language :: Python :: 3.8
Classifier: Programming Language :: Python :: 3.9
Classifier: Development Status :: 5 - Production/Stable
Classifier: Environment :: Web Environment
Classifier: Framework :: Twisted
Classifier: License :: OSI Approved :: GNU Affero General Public License v3 or later (AGPLv3+)
Classifier: Operating System :: POSIX :: Linux
Classifier: Topic :: Communications :: Chat
Requires-Python: >=3.7
License-File: COPYING
Requires-Dist: libervia-backend (<0.9.0,>=0.8.0b1)
Requires-Dist: libervia-templates (<0.9.0,>=0.8.0b1)
Requires-Dist: twisted[tls] (<21.3.0,>=20.3.0)
Requires-Dist: zope.interface (<5.5.0)
Requires-Dist: pyopenssl (<21.0.0)
Requires-Dist: jinja2 (<3.1,>=2.9)
Requires-Dist: shortuuid (<1.1)
Requires-Dist: autobahn (<21.4.0)
Requires-Dist: brython (<3.10,>=3.9.2)
